hucitlib-0.2.9.dist-info/DESCRIPTION.rst
hucitlib-0.2.9.dist-info/METADATA
hucitlib-0.2.9.dist-info/RECORD
hucitlib-0.2.9.dist-info/WHEEL
hucitlib-0.2.9.dist-info/entry_points.txt
hucitlib-0.2.9.dist-info/metadata.json
hucitlib-0.2.9.dist-info/top_level.txt
knowledge_base/__init__.py
knowledge_base/__version__.py
knowledge_base/cli.py
knowledge_base/populate.py
knowledge_base/config/inmemory.ini
knowledge_base/config/inmemory_old.ini
knowledge_base/config/virtuoso.ini
knowledge_base/config/virtuoso_local.ini
knowledge_base/data/kb/dump_000001.ttl
knowledge_base/data/kb/dump_000001.ttl.graph
knowledge_base/data/kb/hucit_000001.ttl
knowledge_base/data/kb/hucit_000001.ttl.graph
knowledge_base/data/kb/hucit_000001.ttl.gz
knowledge_base/data/kb/hucit_000001_withsameas.ttl.gz
knowledge_base/data/kb/kb-all-in-one.ttl
knowledge_base/surfext/__init__.py
