Metadata-Version: 2.0
Name: hucitlib
Version: 0.2.9
Summary: UNKNOWN
Home-page: https://github.com/mromanello/hucit_kb/
Author: Matteo Romanello
Author-email: matteo.romanello@gmail.com
License: GPL v3
Platform: UNKNOWN
Classifier: Intended Audience :: Science/Research
Classifier: Programming Language :: Python :: 2.7
Classifier: Operating System :: POSIX
Requires-Dist: docopt
Requires-Dist: pyCTS
Requires-Dist: surf (>=1.1.9)
